statis/__init__.py
statis/__main__.py
statis/_version.py
statis/cli.py
statis/module.py
statis/monitor.py
statis/notification.py
statis/notifier.py
statis/search.py
statis/units.py
statis/hardware/__init__.py
statis/hardware/cpu.py
statis/hardware/memory.py
statis/modules/__init__.py
statis/modules/battery.py
statis/modules/cpu.py
statis/modules/date.py
statis/modules/memory.py
statis/modules/time.py
statis/notifier_types/__init__.py
statis/notifier_types/memory.py
Statis-1.1.0.dist-info/LICENSE
Statis-1.1.0.dist-info/METADATA
Statis-1.1.0.dist-info/WHEEL
Statis-1.1.0.dist-info/entry_points.txt
Statis-1.1.0.dist-info/top_level.txt
Statis-1.1.0.dist-info/RECORD
