Metadata-Version: 2.1
Name: Statis
Version: 1.1.0
Summary: Modular system monitoring and status display via desktop notifications.
Home-page: https://gitlab.com/BVollmerhaus/statis
Author: Benedikt Vollmerhaus
Author-email: pypi@vollmerhaus.org
License: MIT
Download-URL: https://gitlab.com/BVollmerhaus/statis/-/archive/v1.1.0/statis-v1.1.0.tar.gz
Project-URL: Source Code, https://gitlab.com/BVollmerhaus/statis
Project-URL: Issue Tracker, https://gitlab.com/BVollmerhaus/statis/issues
Keywords: status,system,info,monitoring,notification,extendable,usability
Platform: UNKNOWN
Classifier: Development Status :: 5 - Production/Stable
Classifier: Environment :: Console
Classifier: Environment :: X11 Applications
Classifier: License :: OSI Approved :: MIT License
Classifier: Natural Language :: English
Classifier: Operating System :: POSIX :: Linux
Classifier: Programming Language :: Python :: 3.7
Classifier: Topic :: Desktop Environment
Classifier: Topic :: System :: Monitoring
Requires-Python: >=3.7
Requires-Dist: psutil
Requires-Dist: pytz
